Metadata-Version: 1.0
Name: distributions-parvaresh
Version: 0.1
Summary: Gaussian distributions
Home-page: UNKNOWN
Author: Stephen Parvaresh
Author-email: UNKNOWN
License: UNKNOWN
Platform: UNKNOWN
